patterncounter/__init__.py
patterncounter/__main__.py
patterncounter/counter.py
patterncounter/display.py
patterncounter/operators.py
patterncounter/parser.py
patterncounter/py.typed
patterncounter/sequences.py
patterncounter/visitor.py
patterncounter-0.2.0.dist-info/entry_points.txt
patterncounter-0.2.0.dist-info/LICENSE
patterncounter-0.2.0.dist-info/WHEEL
patterncounter-0.2.0.dist-info/METADATA
patterncounter-0.2.0.dist-info/RECORD
