Metadata-Version: 2.1
Name: patterncounter
Version: 0.2.0
Summary: PatternCounter
Home-page: https://github.com/JoaoFelipe/patterncounter
License: MIT
Author: Joao Felipe Pimentel
Author-email: joaofelipenp@gmail.com
Requires-Python: >=3.8,<4.0
Classifier: Development Status :: 4 - Beta
Classifier: License :: OSI Approved :: MIT License
Classifier: Programming Language :: Python :: 3
Classifier: Programming Language :: Python :: 3.8
Classifier: Programming Language :: Python :: 3.9
Classifier: Programming Language :: Python :: 3.10
Requires-Dist: click (>=8.0.1)
Project-URL: Changelog, https://github.com/JoaoFelipe/patterncounter/releases
Project-URL: Documentation, https://patterncounter.readthedocs.io
Project-URL: Repository, https://github.com/JoaoFelipe/patterncounter
